setuptools_dynamic_dependencies.py
setuptools_dynamic_dependencies-1.0.0.dist-info/AUTHORS
setuptools_dynamic_dependencies-1.0.0.dist-info/LICENSE
setuptools_dynamic_dependencies-1.0.0.dist-info/METADATA
setuptools_dynamic_dependencies-1.0.0.dist-info/WHEEL
setuptools_dynamic_dependencies-1.0.0.dist-info/entry_points.txt
setuptools_dynamic_dependencies-1.0.0.dist-info/top_level.txt
setuptools_dynamic_dependencies-1.0.0.dist-info/RECORD
