Metadata-Version: 2.2
Name: setuptools_dynamic_dependencies
Version: 1.0.0
Summary: A setuptools plugin that allows for dependencies that are dependent on the package's version number.
Author-email: Russell Keith-Magee <russell@keith-magee.com>
Maintainer-email: Russell Keith-Magee <russell@keith-magee.com>
License: Copyright (c) 2022 Russell Keith-Magee.
Project-URL: Project, https://github.com/beeware/setuptools_dynamic_dependencies
Project-URL: Funding, https://beeware.org/contributing/membership/
Project-URL: Tracker, https://github.com/beeware/setuptools_dynamic_dependencies/issues
Project-URL: Source, https://github.com/beeware/setuptools_dynamic_dependencies
Keywords: setuptools,dynamic,dependencies,optional-dependencies,install_requires,extras_require
Classifier: Development Status :: 5 - Production/Stable
Classifier: Intended Audience :: Developers
Classifier: License :: OSI Approved :: BSD License
Classifier: Programming Language :: Python :: 3
Classifier: Programming Language :: Python :: 3.9
Classifier: Programming Language :: Python :: 3.10
Classifier: Programming Language :: Python :: 3.11
Classifier: Programming Language :: Python :: 3.12
Classifier: Programming Language :: Python :: 3.13
Classifier: Programming Language :: Python :: 3.14
Classifier: Programming Language :: Python :: 3 :: Only
Classifier: Topic :: Software Development :: Libraries
Classifier: Topic :: System :: Software Distribution
Classifier: Topic :: Software Development
Classifier: Topic :: Utilities
Requires-Python: >=3.9
License-File: LICENSE
License-File: AUTHORS
Requires-Dist: setuptools>=66.0
Requires-Dist: setuptools_scm>=8.0
Provides-Extra: dev
Requires-Dist: build==1.2.2.post1; extra == "dev"
Requires-Dist: pre-commit==4.0.1; extra == "dev"
Requires-Dist: setuptools_scm==8.1.0; extra == "dev"
Requires-Dist: tox==4.23.2; extra == "dev"
Requires-Dist: twine==6.0.1; extra == "dev"
Requires-Dist: wheel==0.45.1; extra == "dev"
